pyanomaly/__init__.py
pyanomaly/_nbdev.py
pyanomaly/forecast.py
pyanomaly/stats.py
pyanomaly/timeseries.py
pyanomaly/utils.py
pyanomaly-0.0.2.4.dist-info/LICENSE
pyanomaly-0.0.2.4.dist-info/METADATA
pyanomaly-0.0.2.4.dist-info/WHEEL
pyanomaly-0.0.2.4.dist-info/entry_points.txt
pyanomaly-0.0.2.4.dist-info/top_level.txt
pyanomaly-0.0.2.4.dist-info/RECORD
