Metadata-Version: 2.1
Name: pyanomaly
Version: 0.0.2.4
Summary: Time series anomaly detection in Python
Home-page: https://github.com/fillipedem/pyanomaly
Author: Fillipe
Author-email: fillipedem@gmail.com
License: Apache Software License 2.0
Keywords: python anomaly detection time series
Platform: UNKNOWN
Classifier: Development Status :: 3 - Alpha
Classifier: Intended Audience :: Developers
Classifier: License :: OSI Approved :: Apache Software License
Classifier: Natural Language :: English
Classifier: Programming Language :: Python :: 3.6
Classifier: Programming Language :: Python :: 3.7
Classifier: Programming Language :: Python :: 3.8
Requires-Python: >=3.6
Requires-Dist: numpy
Requires-Dist: pandas
Requires-Dist: seaborn
Requires-Dist: matplotlib
Requires-Dist: statsmodels
Requires-Dist: pmdarima
